paranoid_openvpn/__init__.py
paranoid_openvpn/cli.py
paranoid_openvpn/input_handlers.py
paranoid_openvpn/main.py
paranoid_openvpn/profile_parser.py
paranoid_openvpn/py.typed
paranoid_openvpn/types.py
paranoid_openvpn-1.0.0.dist-info/entry_points.txt
paranoid_openvpn-1.0.0.dist-info/LICENSE
paranoid_openvpn-1.0.0.dist-info/WHEEL
paranoid_openvpn-1.0.0.dist-info/METADATA
paranoid_openvpn-1.0.0.dist-info/RECORD
