Metadata-Version: 2.1
Name: paranoid-openvpn
Version: 1.0.0
Summary: Hardening script for OpenVPN client profiles
Home-page: https://github.com/Caligatio/paranoid-openvpn
License: MIT
Author: Brian Turek
Author-email: brian.turek@gmail.com
Requires-Python: >=3.6.1,<4.0.0
Classifier: License :: OSI Approved :: MIT License
Classifier: Programming Language :: Python :: 3
Classifier: Programming Language :: Python :: 3.7
Classifier: Programming Language :: Python :: 3.8
Classifier: Programming Language :: Python :: 3.9
Requires-Dist: typing-extensions (>=3.7.4.3,<4.0.0.0); python_version < "3.8"
Project-URL: Repository, https://github.com/Caligatio/paranoid-openvpn
